test/__init__.py
test/conftest.py
test/functional/__init__.py
test/functional/correctness/__init__.py
test/functional/performance/__init__.py
test/functional/performance/perf_benchmark_runner_test.py
test/integration/__init__.py
test/unit/__init__.py
test/utils/__init__.py
test/utils/api_client.py
test/utils/config.py
test/utils/data.py
test/utils/files.py
test/utils/logging.py
vajra/__init__.py
vajra/_kernels.cpython-310-x86_64-linux-gnu.so
vajra/_native.cpython-310-x86_64-linux-gnu.so
vajra/_version.py
vajra/enums.py
vajra/logger.py
vajra/version.py
vajra/benchmark/__init__.py
vajra/benchmark/benchmark_runner.py
vajra/benchmark/config.py
vajra/benchmark/constants.py
vajra/benchmark/main.py
vajra/benchmark/entities/__init__.py
vajra/benchmark/entities/base_entity.py
vajra/benchmark/entities/request.py
vajra/benchmark/request_generator/__init__.py
vajra/benchmark/request_generator/base_request_generator.py
vajra/benchmark/request_generator/base_request_interval_generator.py
vajra/benchmark/request_generator/base_request_length_generator.py
vajra/benchmark/request_generator/fixed_request_length_generator.py
vajra/benchmark/request_generator/gamma_request_interval_generator.py
vajra/benchmark/request_generator/poisson_request_interval_generator.py
vajra/benchmark/request_generator/request_generator_registry.py
vajra/benchmark/request_generator/request_interval_generator_registry.py
vajra/benchmark/request_generator/request_length_generator_registry.py
vajra/benchmark/request_generator/static_request_interval_generator.py
vajra/benchmark/request_generator/synthetic_request_generator.py
vajra/benchmark/request_generator/trace_request_generator.py
vajra/benchmark/request_generator/trace_request_interval_generator.py
vajra/benchmark/request_generator/trace_request_length_generator.py
vajra/benchmark/request_generator/uniform_request_length_generator.py
vajra/benchmark/request_generator/zipf_request_length_generator.py
vajra/benchmark/utils/__init__.py
vajra_nightly-0.1.dev2025022301.dist-info/LICENSE
vajra_nightly-0.1.dev2025022301.dist-info/METADATA
vajra_nightly-0.1.dev2025022301.dist-info/WHEEL
vajra_nightly-0.1.dev2025022301.dist-info/top_level.txt
vajra_nightly-0.1.dev2025022301.dist-info/RECORD
