Metadata-Version: 2.2
Name: vajra-nightly
Version: 0.1.dev2025022301
Summary: A high-throughput and low-latency LLM inference system
Author: Vajra Team
License: Apache 2.0
Classifier: Programming Language :: Python :: 3.8
Classifier: Programming Language :: Python :: 3.9
Classifier: Programming Language :: Python :: 3.10
Classifier: Programming Language :: Python :: 3.11
Classifier: License :: OSI Approved :: Apache Software License
Classifier: Topic :: Scientific/Engineering :: Artificial Intelligence
Requires-Python: >=3.10
License-File: LICENSE
Requires-Dist: ninja
Requires-Dist: psutil
Requires-Dist: ray>=2.5.1
Requires-Dist: pandas
Requires-Dist: pyarrow
Requires-Dist: sentencepiece
Requires-Dist: numpy
Requires-Dist: torch>=2.5
Requires-Dist: transformers>=4.37.0
Requires-Dist: plotly_express
Requires-Dist: wandb
Requires-Dist: kaleido
Requires-Dist: ddsketch
Requires-Dist: flashinfer-python
Requires-Dist: pillow
Requires-Dist: tiktoken
Requires-Dist: grpcio
Requires-Dist: uvicorn
Requires-Dist: fastapi
Requires-Dist: openai
Requires-Dist: vidur
Requires-Dist: zmq
Dynamic: author
Dynamic: classifier
Dynamic: description
Dynamic: description-content-type
Dynamic: license
Dynamic: requires-dist
Dynamic: requires-python
Dynamic: summary
